rewritebody/__init__.py
rewritebody/compat.py
rewritebody/django/__init__.py
rewritebody-1.0.dist-info/DESCRIPTION.rst
rewritebody-1.0.dist-info/METADATA
rewritebody-1.0.dist-info/RECORD
rewritebody-1.0.dist-info/WHEEL
rewritebody-1.0.dist-info/entry_points.txt
rewritebody-1.0.dist-info/metadata.json
rewritebody-1.0.dist-info/namespace_packages.txt
rewritebody-1.0.dist-info/top_level.txt
